qubicon/__init__.py
qubicon/cli.py
qubicon/core.py
qubicon/api/__init__.py
qubicon/api/client.py
qubicon/api/errors.py
qubicon/api/types.py
qubicon/api/public_api_controller/__init__.py
qubicon/api/public_api_controller/create_computable_model.py
qubicon/api/public_api_controller/create_physical_quantity.py
qubicon/api/public_api_controller/get_channels.py
qubicon/api/public_api_controller/get_equipment_variable_nodes.py
qubicon/api/public_api_controller/get_job.py
qubicon/api/public_api_controller/get_job_artifact.py
qubicon/api/public_api_controller/get_list_of_computable_models.py
qubicon/api/public_api_controller/get_multiplex_chart_data_channels.py
qubicon/api/public_api_controller/get_offline_equipment.py
qubicon/api/public_api_controller/get_online_equipments.py
qubicon/api/public_api_controller/get_physical_quantities.py
qubicon/api/public_api_controller/get_process_groups.py
qubicon/api/public_api_controller/get_processes.py
qubicon/api/public_api_controller/import_offline_equipment_data_file_async.py
qubicon/api/public_api_controller/login.py
qubicon/api/public_api_controller/refresh.py
qubicon/api/public_api_controller/start_export_process_data.py
qubicon/api/public_api_controller/stream_events.py
qubicon/api/public_api_controller_backup_1740758724/__init__.py
qubicon/api/public_api_controller_backup_1740758724/create_computable_model.py
qubicon/api/public_api_controller_backup_1740758724/create_physical_quantity.py
qubicon/api/public_api_controller_backup_1740758724/get_channels.py
qubicon/api/public_api_controller_backup_1740758724/get_equipment_variable_nodes.py
qubicon/api/public_api_controller_backup_1740758724/get_job.py
qubicon/api/public_api_controller_backup_1740758724/get_job_artifact.py
qubicon/api/public_api_controller_backup_1740758724/get_list_of_computable_models.py
qubicon/api/public_api_controller_backup_1740758724/get_multiplex_chart_data_channels.py
qubicon/api/public_api_controller_backup_1740758724/get_offline_equipment.py
qubicon-3.5.16.dist-info/METADATA
qubicon-3.5.16.dist-info/WHEEL
qubicon-3.5.16.dist-info/entry_points.txt
qubicon-3.5.16.dist-info/top_level.txt
qubicon-3.5.16.dist-info/RECORD
