Metadata-Version: 2.1
Name: qubicon
Version: 3.5.16
Summary: Python SDK for interacting with the Qubicon platform through the library or CLI
Home-page: 
Author: Olivier Guillet
Author-email: olivier.guillet@qubicon.io
Classifier: Programming Language :: Python :: 3
Classifier: Operating System :: OS Independent
Requires-Python: >=3.8
Requires-Dist: attrs==25.1.0
Requires-Dist: httpx==0.28.1
Requires-Dist: pandas>=1.5.3
Requires-Dist: rapidfuzz>=3.8.1
Requires-Dist: rich==13.9.4
Requires-Dist: setuptools==68.2.2
Requires-Dist: tabulate==0.9.0
Requires-Dist: requests==2.32.3
Requires-Dist: openpyxl==3.1.5
